sui_python_sdk/__init__.py
sui_python_sdk/models.py
sui_python_sdk/provider.py
sui_python_sdk/rpc_tx_data_serializer.py
sui_python_sdk/signer_with_provider.py
sui_python_sdk/wallet.py
sui_python_sdk-0.1.2.dist-info/METADATA
sui_python_sdk-0.1.2.dist-info/WHEEL
sui_python_sdk-0.1.2.dist-info/top_level.txt
sui_python_sdk-0.1.2.dist-info/RECORD
