Metadata-Version: 2.1
Name: sui-python-sdk
Version: 0.1.2
Author: George
Author-email: georgelombardi97@gmail.com
Classifier: Programming Language :: Python :: 3
Requires-Python: >=3.7
Requires-Dist: httpx
Requires-Dist: pynacl
